pax/__init__.py
pax/cli.py
paxer-1.0.1.dist-info/METADATA
paxer-1.0.1.dist-info/WHEEL
paxer-1.0.1.dist-info/entry_points.txt
paxer-1.0.1.dist-info/top_level.txt
paxer-1.0.1.dist-info/RECORD
